cnmrstar.pypy38-pp73-x86_64-linux-gnu.so
pynmrstar/__init__.py
pynmrstar/_internal.py
pynmrstar/_types.py
pynmrstar/definitions.py
pynmrstar/entry.py
pynmrstar/exceptions.py
pynmrstar/loop.py
pynmrstar/parser.py
pynmrstar/saveframe.py
pynmrstar/schema.py
pynmrstar/utils.py
pynmrstar/reference_files/comments.str
pynmrstar/reference_files/data_types.csv
pynmrstar/reference_files/schema.csv
pynmrstar-3.3.6.dist-info/LICENSE
pynmrstar-3.3.6.dist-info/METADATA
pynmrstar-3.3.6.dist-info/WHEEL
pynmrstar-3.3.6.dist-info/top_level.txt
pynmrstar-3.3.6.dist-info/RECORD
