Metadata-Version: 2.1
Name: pynmrstar
Version: 3.3.6
Summary: PyNMR-STAR provides tools for reading, writing, modifying, and interacting with NMR-STAR files. Maintained by the BMRB.
Home-page: https://github.com/uwbmrb/PyNMRSTAR
Author: Jon Wedell
Author-email: Jon Wedell <wedell@uchc.edu>
License: MIT
Project-URL: Homepage, https://github.com/bmrb-io/PyNMRSTAR
Keywords: bmrb,parser,nmr,nmrstar,biomagresbank,biological magnetic resonance bank
Classifier: Development Status :: 6 - Mature
Classifier: Environment :: Console
Classifier: Programming Language :: Python :: 3 :: Only
Classifier: Programming Language :: Python :: 3.8
Classifier: Programming Language :: Python :: 3.9
Classifier: Programming Language :: Python :: 3.10
Classifier: Programming Language :: Python :: 3.11
Classifier: Programming Language :: Python :: 3.12
Classifier: Programming Language :: Python :: 3.13
Classifier: Intended Audience :: Developers
Classifier: License :: OSI Approved :: MIT License
Classifier: Natural Language :: English
Classifier: Operating System :: MacOS
Classifier: Operating System :: POSIX :: Linux
Classifier: Operating System :: Microsoft :: Windows
Classifier: Topic :: Scientific/Engineering :: Bio-Informatics
Classifier: Topic :: Software Development :: Libraries
Classifier: Topic :: Software Development :: Libraries :: Python Modules
Requires-Python: >=3.7
License-File: LICENSE
Requires-Dist: requests<=3,>=2.21.0
